{"model": {"stream_table": {"index": [0, 1, 2, 3, 4, 5], "columns": ["Variable", "Units", "s01", "s02", "s03"], "data": [["Molar Flow", {"raw": "mole / second", "html": "mol/s", "latex": "\\frac{\\mathrm{mol}}{\\mathrm{s}}"}, [55.5084, "unfixed"], [55.5084, "unfixed"], [111.0168, "unfixed"]], ["Mass Flow", {"raw": "kilogram / second", "html": "kg/s", "latex": "\\frac{\\mathrm{kg}}{\\mathrm{s}}"}, [1.0, "expression"], [1.0, "expression"], [2.0, "expression"]], ["T", {"raw": "kelvin", "html": "K", "latex": "\\mathrm{K}"}, [350.0, "expression"], [450.0, "expression"], [373.1243, "expression"]], ["P", {"raw": "pascal", "html": "Pa", "latex": "\\mathrm{Pa}"}, [101325.0, "unfixed"], [501325.0, "unfixed"], [101325.0, "unfixed"]], ["Vapor Fraction", {"raw": "dimensionless", "html": "", "latex": ""}, [0.0, "expression"], [1.0, "expression"], [0.50723, "expression"]], ["Molar Enthalpy", {"raw": "joule / mole", "html": "J/mol", "latex": "\\frac{\\mathrm{J}}{\\mathrm{mol}}"}, [5798.01829, "unfixed"], [50539.76638, "unfixed"], [28168.89234, "unfixed"]]]}, "id": "Mixer-Model", "unit_models": {"mixer": {"type": "mixer", "image": "/images/icons/mixer.svg", "performance_contents": {}, "stream_contents": {"0": {"Variable": "Molar Flow", "Units": {"raw": "mole / second", "html": "mol/s", "latex": "\\frac{\\mathrm{mol}}{\\mathrm{s}}"}, "inlet_1": 55.5084, "inlet_2": 55.5084, "Outlet": 111.0168}, "1": {"Variable": "Mass Flow", "Units": {"raw": "kilogram / second", "html": "kg/s", "latex": "\\frac{\\mathrm{kg}}{\\mathrm{s}}"}, "inlet_1": 1.0, "inlet_2": 1.0, "Outlet": 2.0}, "2": {"Variable": "T", "Units": {"raw": "kelvin", "html": "K", "latex": "\\mathrm{K}"}, "inlet_1": 350.0, "inlet_2": 450.0, "Outlet": 373.1243}, "3": {"Variable": "P", "Units": {"raw": "pascal", "html": "Pa", "latex": "\\mathrm{Pa}"}, "inlet_1": 101325.0, "inlet_2": 501325.0, "Outlet": 101325.0}, "4": {"Variable": "Vapor Fraction", "Units": {"raw": "dimensionless", "html": "", "latex": ""}, "inlet_1": 0.0, "inlet_2": 1.0, "Outlet": 0.50723}, "5": {"Variable": "Molar Enthalpy", "Units": {"raw": "joule / mole", "html": "J/mol", "latex": "\\frac{\\mathrm{J}}{\\mathrm{mol}}"}, "inlet_1": 5798.01829, "inlet_2": 50539.76638, "Outlet": 28168.89234}}}, "feed1": {"type": "feed", "image": "/images/icons/feed.svg", "performance_contents": {}, "stream_contents": {"0": {"Variable": "Molar Flow", "Units": {"raw": "mole / second", "html": "mol/s", "latex": "\\frac{\\mathrm{mol}}{\\mathrm{s}}"}, "Outlet": 55.5084}, "1": {"Variable": "Mass Flow", "Units": {"raw": "kilogram / second", "html": "kg/s", "latex": "\\frac{\\mathrm{kg}}{\\mathrm{s}}"}, "Outlet": 1.0}, "2": {"Variable": "T", "Units": {"raw": "kelvin", "html": "K", "latex": "\\mathrm{K}"}, "Outlet": 350.0}, "3": {"Variable": "P", "Units": {"raw": "pascal", "html": "Pa", "latex": "\\mathrm{Pa}"}, "Outlet": 101325.0}, "4": {"Variable": "Vapor Fraction", "Units": {"raw": "dimensionless", "html": "", "latex": ""}, "Outlet": 0.0}, "5": {"Variable": "Molar Enthalpy", "Units": {"raw": "joule / mole", "html": "J/mol", "latex": "\\frac{\\mathrm{J}}{\\mathrm{mol}}"}, "Outlet": 5798.01829}}}, "feed2": {"type": "feed", "image": "/images/icons/feed.svg", "performance_contents": {}, "stream_contents": {"0": {"Variable": "Molar Flow", "Units": {"raw": "mole / second", "html": "mol/s", "latex": "\\frac{\\mathrm{mol}}{\\mathrm{s}}"}, "Outlet": 55.5084}, "1": {"Variable": "Mass Flow", "Units": {"raw": "kilogram / second", "html": "kg/s", "latex": "\\frac{\\mathrm{kg}}{\\mathrm{s}}"}, "Outlet": 1.0}, "2": {"Variable": "T", "Units": {"raw": "kelvin", "html": "K", "latex": "\\mathrm{K}"}, "Outlet": 450.0}, "3": {"Variable": "P", "Units": {"raw": "pascal", "html": "Pa", "latex": "\\mathrm{Pa}"}, "Outlet": 501325.0}, "4": {"Variable": "Vapor Fraction", "Units": {"raw": "dimensionless", "html": "", "latex": ""}, "Outlet": 1.0}, "5": {"Variable": "Molar Enthalpy", "Units": {"raw": "joule / mole", "html": "J/mol", "latex": "\\frac{\\mathrm{J}}{\\mathrm{mol}}"}, "Outlet": 50539.76638}}}, "product": {"type": "product", "image": "/images/icons/product.svg", "performance_contents": {}, "stream_contents": {"0": {"Variable": "Molar Flow", "Units": {"raw": "mole / second", "html": "mol/s", "latex": "\\frac{\\mathrm{mol}}{\\mathrm{s}}"}, "Inlet": 111.0168}, "1": {"Variable": "Mass Flow", "Units": {"raw": "kilogram / second", "html": "kg/s", "latex": "\\frac{\\mathrm{kg}}{\\mathrm{s}}"}, "Inlet": 2.0}, "2": {"Variable": "T", "Units": {"raw": "kelvin", "html": "K", "latex": "\\mathrm{K}"}, "Inlet": 373.1243}, "3": {"Variable": "P", "Units": {"raw": "pascal", "html": "Pa", "latex": "\\mathrm{Pa}"}, "Inlet": 101325.0}, "4": {"Variable": "Vapor Fraction", "Units": {"raw": "dimensionless", "html": "", "latex": ""}, "Inlet": 0.50723}, "5": {"Variable": "Molar Enthalpy", "Units": {"raw": "joule / mole", "html": "J/mol", "latex": "\\frac{\\mathrm{J}}{\\mathrm{mol}}"}, "Inlet": 28168.89234}}}}, "arcs": {"s01": {"source": "feed1", "dest": "mixer", "label": "Molar flow 55.5084\nMass flow 1.0\nT 350.0\nP 101325.0\nVapor fraction 0.0\nMolar enthalpy 5798.0182"}, "s02": {"source": "feed2", "dest": "mixer", "label": "Molar flow 55.5084\nMass flow 1.0\nT 450.0\nP 501325.0\nVapor fraction 1.0\nMolar enthalpy 50539.7663"}, "s03": {"source": "mixer", "dest": "product", "label": "Molar flow 111.0168\nMass flow 2.0\nT 373.1243\nP 101325.0\nVapor fraction 0.50723\nMolar enthalpy 28168.8923"}}}, "routing_config": {"s01": {"cell_index": 2, "cell_config": {"gap": {"source": {"x": 30, "y": 0}, "destination": {"x": -30, "y": 0}}}}, "s02": {"cell_index": 4, "cell_config": {"gap": {"source": {"x": 30, "y": 0}, "destination": {"x": -30, "y": 0}}}}, "s03": {"cell_index": 6, "cell_config": {"gap": {"source": {"x": 30, "y": 0}, "destination": {"x": -30, "y": 0}}}}}, "cells": [{"type": "standard.Image", "position": {"x": 0, "y": -120}, "size": {"width": 50, "height": 50}, "angle": 0, "id": "feed1", "z": 1, "ports": {"groups": {"out": {"position": {"name": "left", "args": {"x": 48, "y": 25, "dx": 1, "dy": 1}}, "attrs": {"rect": {"stroke": "#000000", "stroke-width": 0, "width": 0, "height": 0}}, "markup": "<g><rect/></g>"}}, "items": [{"group": "out", "id": 0}]}, "attrs": {"image": {"xlinkHref": "/images/icons/feed.svg"}, "label": {"text": "feed1"}, "root": {"title": "feed"}}}, {"type": "standard.Image", "position": {"x": 150, "y": 0}, "size": {"width": 50, "height": 50}, "angle": 0, "id": "mixer", "z": 1, "ports": {"groups": {"in": {"position": {"name": "left", "args": {}}, "attrs": {"rect": {"stroke": "#000000", "stroke-width": 0, "width": 0, "height": 0}}, "markup": "<g><rect/></g>"}, "out": {"position": {"name": "left", "args": {"x": 48, "y": 25, "dx": 1, "dy": 1}}, "attrs": {"rect": {"stroke": "#000000", "stroke-width": 0, "width": 0, "height": 0}}, "markup": "<g><rect/></g>"}}, "items": [{"group": "in", "id": 1}, {"group": "in", "id": 3}, {"group": "out", "id": 4}]}, "attrs": {"image": {"xlinkHref": "/images/icons/mixer.svg"}, "label": {"text": "mixer"}, "root": {"title": "mixer"}}}, {"type": "standard.Link", "source": {"id": "feed1", "port": 0}, "target": {"id": "mixer", "port": 1}, "router": {"name": "manhattan", "padding": 10}, "connector": {"name": "jumpover", "attrs": {"line": {"stroke": "#5c9adb"}}}, "id": "s01", "attrs": {"line": {"stroke": "#979797", "stroke-width": 2}}, "labels": [{"attrs": {"rect": {"fill": "#d7dce0", "stroke": "white", "stroke-width": 0, "fill-opacity": 0}, "text": {"text": "Molar flow 55.5084\nMass flow 1.0\nT 350.0\nP 101325.0\nVapor fraction 0.0\nMolar enthalpy 5798.0182", "fill": "black", "text-anchor": "left", "display": "none"}}, "position": {"distance": 0.66, "offset": -40}}, {"attrs": {"text": {"text": "s01"}}}], "z": 2}, {"type": "standard.Image", "position": {"x": 0, "y": 120}, "size": {"width": 50, "height": 50}, "angle": 0, "id": "feed2", "z": 1, "ports": {"groups": {"out": {"position": {"name": "left", "args": {"x": 48, "y": 25, "dx": 1, "dy": 1}}, "attrs": {"rect": {"stroke": "#000000", "stroke-width": 0, "width": 0, "height": 0}}, "markup": "<g><rect/></g>"}}, "items": [{"group": "out", "id": 2}]}, "attrs": {"image": {"xlinkHref": "/images/icons/feed.svg"}, "label": {"text": "feed2"}, "root": {"title": "feed"}}}, {"type": "standard.Link", "source": {"id": "feed2", "port": 2}, "target": {"id": "mixer", "port": 3}, "router": {"name": "manhattan", "padding": 10}, "connector": {"name": "jumpover", "attrs": {"line": {"stroke": "#5c9adb"}}}, "id": "s02", "attrs": {"line": {"stroke": "#979797", "stroke-width": 2}}, "labels": [{"attrs": {"rect": {"fill": "#d7dce0", "stroke": "white", "stroke-width": 0, "fill-opacity": 0}, "text": {"text": "Molar flow 55.5084\nMass flow 1.0\nT 450.0\nP 501325.0\nVapor fraction 1.0\nMolar enthalpy 50539.7663", "fill": "black", "text-anchor": "left", "display": "none"}}, "position": {"distance": 0.66, "offset": -40}}, {"attrs": {"text": {"text": "s02"}}}], "z": 2}, {"type": "standard.Image", "position": {"x": 300, "y": 0}, "size": {"width": 50, "height": 50}, "angle": 0, "id": "product", "z": 1, "ports": {"groups": {"in": {"position": {"name": "left", "args": {"x": 2, "y": 25, "dx": 1, "dy": 1}}, "attrs": {"rect": {"stroke": "#000000", "stroke-width": 0, "width": 0, "height": 0}}, "markup": "<g><rect/></g>"}}, "items": [{"group": "in", "id": 5}]}, "attrs": {"image": {"xlinkHref": "/images/icons/product.svg"}, "label": {"text": "product"}, "root": {"title": "product"}}}, {"type": "standard.Link", "source": {"id": "mixer", "port": 4}, "target": {"id": "product", "port": 5}, "router": {"name": "manhattan", "padding": 10}, "connector": {"name": "jumpover", "attrs": {"line": {"stroke": "#5c9adb"}}}, "id": "s03", "attrs": {"line": {"stroke": "#979797", "stroke-width": 2}}, "labels": [{"attrs": {"rect": {"fill": "#d7dce0", "stroke": "white", "stroke-width": 0, "fill-opacity": 0}, "text": {"text": "Molar flow 111.0168\nMass flow 2.0\nT 373.1243\nP 101325.0\nVapor fraction 0.50723\nMolar enthalpy 28168.8923", "fill": "black", "text-anchor": "left", "display": "none"}}, "position": {"distance": 0.66, "offset": -40}}, {"attrs": {"text": {"text": "s03"}}}], "z": 2}]}